{"cameraMode":{"drawMode":0,"name":"Shaded","section":"Shading Mode"},"sceneLighting":false,"audioPlay":false,"sceneViewState":{"m_AlwaysRefresh":false,"showFog":true,"showSkybox":false,"showFlares":true,"showImageEffects":true,"showParticleSystems":true,"showVisualEffectGraphs":true,"m_FxEnabled":true},"in2DMode":false,"pivot":{"x":-8.942495346069336,"y":2.6287403106689455,"z":-9.430086135864258},"rotation":{"x":-0.22901377081871034,"y":0.6103162169456482,"z":-0.1903918981552124,"w":-0.7340784072875977},"size":11.660304069519043,"orthographic":false}